pygeomodeling/__init__.py
pygeomodeling/confidence_scoring.py
pygeomodeling/cross_validation.py
pygeomodeling/exceptions.py
pygeomodeling/facies.py
pygeomodeling/formation_tops.py
pygeomodeling/grdecl_parser.py
pygeomodeling/integration_exports.py
pygeomodeling/kriging.py
pygeomodeling/log_features.py
pygeomodeling/model_gp.py
pygeomodeling/parallel.py
pygeomodeling/plot.py
pygeomodeling/reservoir_engineering.py
pygeomodeling/serialization.py
pygeomodeling/spe9_toolkit.py
pygeomodeling/toolkit.py
pygeomodeling/unified_toolkit.py
pygeomodeling/variogram.py
pygeomodeling/variogram_plot.py
pygeomodeling/well_data.py
pygeomodeling/well_log_processor.py
pygeomodeling/workflow_manager.py
pygeomodeling/data/SPE9.GRDECL
pygeomodeling/data/__init__.py
pygeomodeling/experiments/__init__.py
pygeomodeling/experiments/deep_gp_experiment.py
pygeomodeling-0.3.2.dist-info/licenses/LICENSE
pygeomodeling-0.3.2.dist-info/METADATA
pygeomodeling-0.3.2.dist-info/WHEEL
pygeomodeling-0.3.2.dist-info/entry_points.txt
pygeomodeling-0.3.2.dist-info/top_level.txt
pygeomodeling-0.3.2.dist-info/RECORD
