Metadata-Version: 2.4
Name: pygeomodeling
Version: 0.3.2
Summary: Advanced Gaussian Process Regression and Kriging toolkit for SPE9 reservoir modeling
Author: Kyle T. Jones
Author-email: "K. Jones" <kyletjones@gmail.com>
Maintainer-email: "K. Jones" <kyletjones@gmail.com>
License: MIT
Project-URL: Homepage, https://github.com/kylejones200/pygeomodeling
Project-URL: Repository, https://github.com/kylejones200/pygeomodeling
Project-URL: Documentation, https://github.com/kylejones200/pygeomodeling#readme
Project-URL: Bug Tracker, https://github.com/kylejones200/pygeomodeling/issues
Keywords: geomodeling,GPR,kriging,SPE9,reservoir,gaussian-process,geostatistics
Classifier: Development Status :: 4 - Beta
Classifier: Programming Language :: Python :: 3
Classifier: Programming Language :: Python :: 3.9
Classifier: Programming Language :: Python :: 3.10
Classifier: Programming Language :: Python :: 3.11
Classifier: Programming Language :: Python :: 3.12
Classifier: Intended Audience :: Science/Research
Classifier: License :: OSI Approved :: MIT License
Classifier: Topic :: Scientific/Engineering :: Hydrology
Classifier: Topic :: Scientific/Engineering :: Mathematics
Classifier: Topic :: Scientific/Engineering :: Physics
Requires-Python: >=3.9
License-File: LICENSE
Requires-Dist: numpy<2.0.0,>=1.24.0
Requires-Dist: pandas<3.0.0,>=1.5.0
Requires-Dist: scipy<2.0.0,>=1.10.0
Requires-Dist: scikit-learn<2.0.0,>=1.3.0
Requires-Dist: joblib<2.0.0,>=1.2.0
Requires-Dist: matplotlib<4.0.0,>=3.7.0
Requires-Dist: signalplot>=0.1.0
Requires-Dist: pykrige<2.0.0,>=1.6.0
Requires-Dist: gstools<2.0.0,>=1.4.0
Requires-Dist: numba<1.0.0,>=0.58.0
Requires-Dist: tqdm<5.0.0,>=4.65.0
Provides-Extra: dev
Requires-Dist: jupyter<2.0.0,>=1.0.0; extra == "dev"
Requires-Dist: ipykernel<7.0.0,>=6.20.0; extra == "dev"
Requires-Dist: black>=23.0.0; extra == "dev"
Requires-Dist: pytest>=7.0.0; extra == "dev"
Requires-Dist: pytest-cov>=4.0.0; extra == "dev"
Requires-Dist: pytest-xdist>=3.0.0; extra == "dev"
Requires-Dist: pytest-mock>=3.10.0; extra == "dev"
Requires-Dist: pytest-timeout>=2.1.0; extra == "dev"
Requires-Dist: coverage>=7.0.0; extra == "dev"
Requires-Dist: flake8>=6.0.0; extra == "dev"
Requires-Dist: mypy>=1.0.0; extra == "dev"
Requires-Dist: ruff>=0.6.0; extra == "dev"
Provides-Extra: advanced
Requires-Dist: torch<3.0.0,>=2.0.0; extra == "advanced"
Requires-Dist: gpytorch<2.0.0,>=1.11.0; extra == "advanced"
Requires-Dist: botorch<1.0.0,>=0.8.0; extra == "advanced"
Requires-Dist: optuna<4.0.0,>=3.2.0; extra == "advanced"
Provides-Extra: geospatial
Requires-Dist: rasterio<2.0.0,>=1.3.0; extra == "geospatial"
Requires-Dist: fiona<2.0.0,>=1.9.0; extra == "geospatial"
Requires-Dist: geopandas<1.0.0,>=0.13.0; extra == "geospatial"
Requires-Dist: shapely<3.0.0,>=2.0.0; extra == "geospatial"
Requires-Dist: xarray<2024.0.0,>=2023.1.0; extra == "geospatial"
Requires-Dist: netcdf4<2.0.0,>=1.6.0; extra == "geospatial"
Requires-Dist: h5py<4.0.0,>=3.8.0; extra == "geospatial"
Provides-Extra: performance
Requires-Dist: cupy<13.0.0,>=12.0.0; extra == "performance"
Provides-Extra: visualization
Provides-Extra: docs
Requires-Dist: mkdocs>=1.5.0; extra == "docs"
Requires-Dist: mkdocs-material>=9.0.0; extra == "docs"
Requires-Dist: mkdocstrings[python]>=0.20.0; extra == "docs"
Requires-Dist: pymdown-extensions>=10.0.0; extra == "docs"
Provides-Extra: all
Requires-Dist: torch<3.0.0,>=2.0.0; extra == "all"
Requires-Dist: gpytorch<2.0.0,>=1.11.0; extra == "all"
Requires-Dist: botorch<1.0.0,>=0.8.0; extra == "all"
Requires-Dist: optuna<4.0.0,>=3.2.0; extra == "all"
Requires-Dist: rasterio<2.0.0,>=1.3.0; extra == "all"
Requires-Dist: fiona<2.0.0,>=1.9.0; extra == "all"
Requires-Dist: geopandas<1.0.0,>=0.13.0; extra == "all"
Requires-Dist: shapely<3.0.0,>=2.0.0; extra == "all"
Requires-Dist: xarray<2024.0.0,>=2023.1.0; extra == "all"
Requires-Dist: netcdf4<2.0.0,>=1.6.0; extra == "all"
Requires-Dist: h5py<4.0.0,>=3.8.0; extra == "all"
Requires-Dist: jupyter<2.0.0,>=1.0.0; extra == "all"
Requires-Dist: ipykernel<7.0.0,>=6.20.0; extra == "all"
Requires-Dist: black>=23.0.0; extra == "all"
Requires-Dist: pytest>=7.0.0; extra == "all"
Requires-Dist: pytest-cov>=4.0.0; extra == "all"
Requires-Dist: pytest-xdist>=3.0.0; extra == "all"
Requires-Dist: pytest-mock>=3.10.0; extra == "all"
Requires-Dist: pytest-timeout>=2.1.0; extra == "all"
Requires-Dist: coverage>=7.0.0; extra == "all"
Requires-Dist: flake8>=6.0.0; extra == "all"
Requires-Dist: mypy>=1.0.0; extra == "all"
Requires-Dist: pre-commit>=3.0.0; extra == "all"
Requires-Dist: mkdocs>=1.5.0; extra == "all"
Requires-Dist: mkdocs-material>=9.0.0; extra == "all"
Requires-Dist: mkdocstrings[python]>=0.20.0; extra == "all"
Requires-Dist: pymdown-extensions>=10.0.0; extra == "all"
Dynamic: author
Dynamic: license-file
Dynamic: requires-python
